odoo10_addon_product_categ_image-10.0.1.0.1-py3.8-nspkg.pth
odoo/addons/product_categ_image/README.rst
odoo/addons/product_categ_image/__init__.py
odoo/addons/product_categ_image/__manifest__.py
odoo/addons/product_categ_image/i18n/product_categ_image.pot
odoo/addons/product_categ_image/models/__init__.py
odoo/addons/product_categ_image/models/product_category.py
odoo/addons/product_categ_image/static/description/icon.png
odoo/addons/product_categ_image/views/product_view.xml
odoo10_addon_product_categ_image-10.0.1.0.1.dist-info/METADATA
odoo10_addon_product_categ_image-10.0.1.0.1.dist-info/WHEEL
odoo10_addon_product_categ_image-10.0.1.0.1.dist-info/namespace_packages.txt
odoo10_addon_product_categ_image-10.0.1.0.1.dist-info/top_level.txt
odoo10_addon_product_categ_image-10.0.1.0.1.dist-info/RECORD
